README.md
setup.py
swork.py
swork_version.py
bin/swork
swork.egg-info/PKG-INFO
swork.egg-info/SOURCES.txt
swork.egg-info/dependency_links.txt
swork.egg-info/requires.txt
swork.egg-info/top_level.txt
swork.egg-info/zip-safe
sworklib/__init__.py
sworklib/lib.py