Metadata-Version: 1.1
Name: swork
Version: 0.6
Summary: A shell enviroment manager. Allows you to easily manage the shell enviroment forworking on various projects.
Home-page: https://www.github.com/timtadh/swork/tree/0.6
Author: Tim Henderson
Author-email: tim.tadh@gmail.com
License: GPLv2
Platform: unix
Provides: swork
